MANIFEST.in
README.rst
setup.py
prob2020/__init__.py
prob2020/console/__init__.py
prob2020/console/annotate.py
prob2020/console/count_frameshifts.py
prob2020/console/extract_gene_seq.py
prob2020/console/probabilistic2020.py
prob2020/console/randomization_test.py
prob2020/console/simulate_non_silent_ratio.py
prob2020/cpp/__init__.py
prob2020/cpp/permutation.hpp
prob2020/cython/__init__.py
prob2020/cython/cutils.cpp
prob2020/python/__init__.py
prob2020/python/amino_acid.py
prob2020/python/annotate.py
prob2020/python/bed_line.py
prob2020/python/count_frameshifts.py
prob2020/python/gene_sequence.py
prob2020/python/indel.py
prob2020/python/mutation_context.py
prob2020/python/mymath.py
prob2020/python/p_value.py
prob2020/python/permutation.py
prob2020/python/process_result.py
prob2020/python/scores.py
prob2020/python/sequence_context.py
prob2020/python/utils.py
probabilistic2020.egg-info/PKG-INFO
probabilistic2020.egg-info/SOURCES.txt
probabilistic2020.egg-info/dependency_links.txt
probabilistic2020.egg-info/entry_points.txt
probabilistic2020.egg-info/requires.txt
probabilistic2020.egg-info/top_level.txt