Metadata-Version: 1.1
Name: probabilistic2020
Version: 1.2.2
Summary: Probabilistic 20/20
Home-page: https://github.com/KarchinLab/probabilistic2020
Author: Collin Tokheim
Author-email: fake@gmail.com
License: Apache License, Version 2.0
Platform: UNKNOWN
Classifier: Topic :: Scientific/Engineering :: Bio-Informatics
Classifier: Environment :: Console
Classifier: Intended Audience :: Developers
Classifier: Intended Audience :: Science/Research
